gpt4zero.py
Gpt4Zero-0.1.1.dist-info/METADATA
Gpt4Zero-0.1.1.dist-info/WHEEL
Gpt4Zero-0.1.1.dist-info/top_level.txt
Gpt4Zero-0.1.1.dist-info/RECORD
