Metadata-Version: 2.2
Name: Gpt4Zero
Version: 0.1.1
Summary: Gpt4Zero - python библиотека для бесплатного взаимодействия с передовыми нейросетями.
Classifier: Programming Language :: Python :: 3
Classifier: Operating System :: OS Independent
Requires-Python: >=3.6
Requires-Dist: requests
Dynamic: classifier
Dynamic: description
Dynamic: description-content-type
Dynamic: requires-dist
Dynamic: requires-python
Dynamic: summary
